deep_astro_uda/__init__.py
deep_astro_uda/client/__init__.py
deep_astro_uda/client/astro_app.py
deep_astro_uda/client/commands/demo_command.py
deep_astro_uda/client/commands/infer_command.py
deep_astro_uda/client/commands/run_command.py
deep_astro_uda/client/options.py
deep_astro_uda/configs/__init__.py
deep_astro_uda/configs/config.yaml
deep_astro_uda/configs/config_functions.py
deep_astro_uda/data_utils/__init__.py
deep_astro_uda/data_utils/download_data.py
deep_astro_uda/dist/__init__.py
deep_astro_uda/dist/deep_astro_uda-0.1.0.tar.gz
deep_astro_uda/model/__init__.py
deep_astro_uda/model/eval.py
deep_astro_uda/model/get_loader.py
deep_astro_uda/model/loss.py
deep_astro_uda/model/lr_schedule.py
deep_astro_uda/model/train.py
deep_astro_uda/settings.py
deep_astro_uda/tuner/tuner.py
deep_astro_uda/utils/__init__.py
deep_astro_uda/utils/utils.py
deep_astro_uda-0.3.5.dist-info/LICENSE
deep_astro_uda-0.3.5.dist-info/METADATA
deep_astro_uda-0.3.5.dist-info/WHEEL
deep_astro_uda-0.3.5.dist-info/entry_points.txt
deep_astro_uda-0.3.5.dist-info/RECORD
