Metadata-Version: 2.1
Name: deep-astro-uda
Version: 0.3.5
Summary: 
Author: Ashia Lewis
Author-email: pantagruelspendulum@protonmail.com
Requires-Python: >=3.9,<4.0
Classifier: Programming Language :: Python :: 3
Classifier: Programming Language :: Python :: 3.9
Classifier: Programming Language :: Python :: 3.10
Classifier: Programming Language :: Python :: 3.11
Requires-Dist: astronn (>=1.1.0,<2.0.0)
Requires-Dist: cleo (>=2.0.1,<3.0.0)
Requires-Dist: numpy (>=1.24.3,<2.0.0)
Requires-Dist: pillow (>=9.5.0,<10.0.0)
Requires-Dist: pyyaml (>=6.0,<7.0)
